{
    "output_dir": "/home/akkumar/ALCIE/OFA_trained_models_memory_baseline/accessories",
    "model_name_or_path": "/home/akkumar/ALCIE/OFA-large-caption",
    "train_caption_file": "/home/akkumar/ALCIE/cluster_facade_training_combined/accessories/train_caption.jsonl",
    "train_image_file": "/home/akkumar/ALCIE/cluster_facade_training_combined/accessories/train_image.tsv",
    "test_caption_file": "",
    "test_image_file": "",
    "freeze_encoder": false,
    "freeze_word_embed": false,
    "num_train_epochs": 20,
    "max_steps": -1,
    "per_device_train_batch_size": 64,
    "per_device_eval_batch_size": 64,
    "learning_rate": 5e-05,
    "max_seq_length": 512,
    "logging_steps": 100,
    "save_steps": 1000,
    "save_total_limit": 3,
    "lr_scheduler_type": "constant",
    "warmup_steps": 500,
    "warmup_ratio": 0,
    "gradient_accumulation_steps": 1,
    "optim": "adamw_torch",
    "seed": 42,
    "fp16": true,
    "no_cuda": false,
    "dataloader_num_workers": 12,
    "save_strategy": "steps",
    "evaluation_strategy": "steps",
    "eval_steps": 1000,
    "weight_decay": 0,
    "max_grad_norm": 1.0,
    "remove_unused_columns": false
  }